meashub/__init__.py
meashub/meashub.py
meashub_access_api-1.0.4.dist-info/METADATA
meashub_access_api-1.0.4.dist-info/WHEEL
meashub_access_api-1.0.4.dist-info/top_level.txt
meashub_access_api-1.0.4.dist-info/RECORD
