Metadata-Version: 2.4
Name: meashub-access-api
Version: 1.0.4
Summary: meashub access api for meashub.iap.tuwien.ac.at
Home-page: https://gitlab.tuwien.ac.at/iap/aip/anp/datasience-projects/meashub-api.git
Author: Johannes Prisslan, Richard van Nieuwenhoven
Author-email: johannes.prisslan@tuwien.ac.at
Project-URL: Homepage, https://meashub.iap.tuwien.ac.at
Keywords: todo
Classifier: Programming Language :: Python :: 3
Classifier: License :: OSI Approved :: MIT License
Classifier: Operating System :: OS Independent
Requires-Python: >=3.1
Dynamic: author
Dynamic: author-email
Dynamic: classifier
Dynamic: description
Dynamic: description-content-type
Dynamic: home-page
Dynamic: keywords
Dynamic: project-url
Dynamic: requires-python
Dynamic: summary
